snappyko/__init__.py
snappyko/knots.py
snappyko/newton.py
snappyko/orbit.py
snappyko/tsorbit.py
snappyko/utils.py
snappyko/version.py
snappyko/xy5.py
snappyko/xyz5.py
SnappyKO-0.5.7.dist-info/LICENSE
SnappyKO-0.5.7.dist-info/METADATA
SnappyKO-0.5.7.dist-info/WHEEL
SnappyKO-0.5.7.dist-info/top_level.txt
SnappyKO-0.5.7.dist-info/RECORD
